setup.py
vicosj_probabilities/Binomialdistribution.py
vicosj_probabilities/Gaussiandistribution.py
vicosj_probabilities/Generaldistribution.py
vicosj_probabilities/__init__.py
vicosj_probabilities.egg-info/PKG-INFO
vicosj_probabilities.egg-info/SOURCES.txt
vicosj_probabilities.egg-info/dependency_links.txt
vicosj_probabilities.egg-info/not-zip-safe
vicosj_probabilities.egg-info/top_level.txt